ntgcalls.cpython-314-x86_64-linux-gnu.so
ntgcalls-2.0.7.dist-info/METADATA
ntgcalls-2.0.7.dist-info/WHEEL
ntgcalls-2.0.7.dist-info/top_level.txt
ntgcalls-2.0.7.dist-info/RECORD
ntgcalls-2.0.7.dist-info/licenses/LICENSE
