Metadata-Version: 2.4
Name: ntgcalls
Version: 2.0.7
Summary: A Native Implementation of Telegram Calls in a seamless way.
Author-email: Laky-64 <iraci.matteo@gmail.com>
Project-URL: Homepage, https://pytgcalls.github.io/
Project-URL: Repository, https://github.com/pytgcalls/ntgcalls.git
Project-URL: Documentation, https://pytgcalls.github.io/NTgCalls
Project-URL: Changelog, https://pytgcalls.github.io/PyTgCalls/Changelogs
Keywords: audio,python,library,video,telegram,stream,ffmpeg,cpp,webrtc,voice-chat,voip,group-chat,video-calls,calls,video-chat,pytgcalls,ntgcalls,tgcalls,py-tgcalls
Classifier: Programming Language :: Python :: 3
Classifier: Programming Language :: Python :: 3 :: Only
Classifier: Programming Language :: Python :: 3.10
Classifier: Programming Language :: Python :: 3.11
Classifier: Programming Language :: Python :: 3.12
Classifier: Programming Language :: Python :: 3.13
Classifier: Programming Language :: Python :: 3.14
Classifier: Programming Language :: Python :: Implementation :: CPython
Requires-Python: >=3.10
License-File: LICENSE
Provides-Extra: test
Requires-Dist: pytest>=6.0; extra == "test"
Dynamic: license-file
